oekofen_api/__init__.py
oekofen_api/const.py
oekofen_api/dummy_oekofen_server.py
oekofen_api-0.0.25.dist-info/LICENSE
oekofen_api-0.0.25.dist-info/METADATA
oekofen_api-0.0.25.dist-info/WHEEL
oekofen_api-0.0.25.dist-info/top_level.txt
oekofen_api-0.0.25.dist-info/RECORD
