Metadata-Version: 2.1
Name: oekofen-api
Version: 0.0.25
Summary: A python library to retrieve statistics from your Oekofen Pelletronic
Home-page: https://github.com/ckarrie/oekofen-api
Download-URL: https://github.com/ckarrie/oekofen-api/archive/refs/tags/v0.0.25.tar.gz
Author: Christian Karrié
Author-email: ckarrie@gmail.com
Classifier: Programming Language :: Python :: 3
Classifier: License :: OSI Approved :: MIT License
Classifier: Operating System :: OS Independent
License-File: LICENSE
Requires-Dist: voluptuous >=0.13.1
Requires-Dist: yarl >=1.8.1
